lcmutils/__init__.py
lcmutils/daemon.py
lcmutils/registry.py
lcmutils/typing.py
lcmutils-0.2.0.dist-info/METADATA
lcmutils-0.2.0.dist-info/WHEEL
lcmutils-0.2.0.dist-info/RECORD
