Metadata-Version: 2.4
Name: lcmutils
Version: 0.2.0
Summary: Python utility library for Lightweight Communications and Marshalling (LCM).
Author-email: Kevin Barnard <kbarnard@mbari.org>
Maintainer-email: Kevin Barnard <kbarnard@mbari.org>
Classifier: License :: OSI Approved :: MIT License
Classifier: Operating System :: OS Independent
Requires-Python: >=3.8
Requires-Dist: lcm>=1.5.0
